MANIFEST.in
ez_setup.py
setup.py
GauminIpuin.egg-info/PKG-INFO
GauminIpuin.egg-info/SOURCES.txt
GauminIpuin.egg-info/dependency_links.txt
GauminIpuin.egg-info/top_level.txt
ipuin/__init__.py
ipuin/ipuin.py
ipuin/step.py
ipuin/test_game.py
ipuin/test_manifest.py
ipuin/uix.py
ipuin/games/__init__.py
ipuin/games/base.py
ipuin/games/choose_one.kv
ipuin/games/choose_one.py
ipuin/games/connect.kv
ipuin/games/connect.py
ipuin/games/mark_correct.kv
ipuin/games/mark_correct.py
ipuin/games/reorder.kv
ipuin/games/reorder.py
ipuin/games/reorder_sentences.kv
ipuin/games/reorder_sentences.py
ipuin/games/riddle.kv
ipuin/games/riddle.py
ipuin/imgs/empty.png
ipuin/tests/__init__.py
ipuin/tests/test_ipuin.py