Metadata-Version: 1.0
Name: GauminIpuin
Version: 0.2
Summary: Interactive book library
Home-page: http://lagunak.gisa-elkartea.org/projects/gauminipuin/
Author: Ales Zabala Alava (Shagi)
Author-email: shagi@gisa-elkartea.org
License: GPLv3+
Platform: UNKNOWN
